{
	"name": "background-color-change",
	"description": "カスタム背景色を選択し、リアルタイムでコントラスト再計算を行う機能",
	"language": "ja",
	"phase": "implementation",
	"created_at": "2025-12-23T06:00:00.000Z",
	"updated_at": "2025-12-29T04:52:00.000Z",
	"approvals": {
		"requirements": {
			"generated": true,
			"approved": true
		},
		"design": {
			"generated": true,
			"approved": true
		},
		"tasks": {
			"generated": true,
			"approved": true
		}
	},
	"codex_reviews": {
		"requirements": {
			"review_count": 2,
			"final_verdict": "OK",
			"session_id": "019b6846-5efa-7931-b126-8bf369b0c8d6",
			"resolved_issues": 4
		},
		"design": {
			"review_count": 3,
			"final_verdict": "GO",
			"session_id": "019b6850-b349-70a0-b155-191b727d4397",
			"resolved_issues": 3,
			"notes": "5.5/5.6 シェード画面背景色追従を追加、GO判定"
		},
		"tasks": {
			"review_count": 1,
			"final_verdict": "APPROVED",
			"session_id": "019b6866-208c-7500-a4be-18912c756360",
			"resolved_issues": 4,
			"notes": "medium 2件（localStorage復元時モード再計算、統合テスト追加）、minor 2件を修正"
		},
		"impl_task_1_1": {
			"review_count": 2,
			"final_verdict": "APPROVED",
			"session_id": "019b6879-3fe3-76a2-aaae-2ae2d6d3485c",
			"resolved_issues": 2,
			"notes": "DemoStateテストの新規フィールド追加、DEFAULT_STATEの背景色デフォルト検証を修正"
		},
		"impl_task_1_2": {
			"review_count": 2,
			"final_verdict": "APPROVED",
			"session_id": "019b6918-a07c-7961-924b-f44c9d7c23fd",
			"resolved_issues": 0,
			"notes": "localStorage永続化関数の実装完了。後続タスクで呼び出し統合予定。"
		}
	}
}
